Metadata-Version: 2.4
Name: timeplus-sqlmesh
Version: 1.0.0
Summary: SQLMesh with Timeplus streaming database support - Next-generation data transformation framework
Author-email: Timeplus <help@timeplus.com>, "TobikoData Inc." <engineering@tobikodata.com>
License:                                  Apache License
Project-URL: Homepage, https://www.timeplus.com/
Project-URL: Documentation, https://docs.timeplus.com/
Project-URL: Repository, https://github.com/timeplus-io/sqlmesh
Project-URL: Issues, https://github.com/timeplus-io/sqlmesh/issues
Project-URL: Upstream SQLMesh, https://github.com/TobikoData/sqlmesh
Classifier: Intended Audience :: Developers
Classifier: Intended Audience :: Science/Research
Classifier: License :: OSI Approved :: Apache Software License
Classifier: Operating System :: OS Independent
Classifier: Programming Language :: SQL
Classifier: Programming Language :: Python :: 3 :: Only
Requires-Python: >=3.9
License-File: LICENSE
Requires-Dist: astor
Requires-Dist: click
Requires-Dist: croniter
Requires-Dist: duckdb!=0.10.3,>=0.10.0
Requires-Dist: dateparser<=1.2.1
Requires-Dist: humanize
Requires-Dist: hyperscript>=0.1.0
Requires-Dist: importlib-metadata; python_version < "3.12"
Requires-Dist: ipywidgets
Requires-Dist: jinja2
Requires-Dist: packaging
Requires-Dist: pandas
Requires-Dist: pydantic>=2.0.0
Requires-Dist: python-dotenv
Requires-Dist: requests
Requires-Dist: rich[jupyter]
Requires-Dist: ruamel.yaml
Requires-Dist: timeplus-sqlglot[rs]>=0.1.0
Requires-Dist: tenacity
Requires-Dist: time-machine
Requires-Dist: json-stream
Provides-Extra: athena
Requires-Dist: PyAthena[Pandas]; extra == "athena"
Provides-Extra: azuresql
Requires-Dist: pymssql; extra == "azuresql"
Provides-Extra: azuresql-odbc
Requires-Dist: pyodbc>=5.0.0; extra == "azuresql-odbc"
Provides-Extra: bigquery
Requires-Dist: google-cloud-bigquery[pandas]; extra == "bigquery"
Requires-Dist: google-cloud-bigquery-storage; extra == "bigquery"
Provides-Extra: bigframes
Requires-Dist: bigframes>=1.32.0; extra == "bigframes"
Provides-Extra: clickhouse
Requires-Dist: clickhouse-connect; extra == "clickhouse"
Provides-Extra: timeplus
Requires-Dist: timeplus-connect; extra == "timeplus"
Provides-Extra: databricks
Requires-Dist: databricks-sql-connector[pyarrow]; extra == "databricks"
Provides-Extra: dev
Requires-Dist: agate; extra == "dev"
Requires-Dist: beautifulsoup4; extra == "dev"
Requires-Dist: clickhouse-connect; extra == "dev"
Requires-Dist: timeplus-connect; extra == "dev"
Requires-Dist: cryptography<46.0.0; extra == "dev"
Requires-Dist: databricks-sql-connector; extra == "dev"
Requires-Dist: dbt-bigquery; extra == "dev"
Requires-Dist: dbt-core; extra == "dev"
Requires-Dist: dbt-duckdb>=1.7.1; extra == "dev"
Requires-Dist: dbt-snowflake!=1.10.1; extra == "dev"
Requires-Dist: dbt-athena-community; extra == "dev"
Requires-Dist: dbt-clickhouse; extra == "dev"
Requires-Dist: dbt-databricks; extra == "dev"
Requires-Dist: dbt-redshift; extra == "dev"
Requires-Dist: dbt-trino; extra == "dev"
Requires-Dist: Faker; extra == "dev"
Requires-Dist: google-auth; extra == "dev"
Requires-Dist: google-cloud-bigquery; extra == "dev"
Requires-Dist: google-cloud-bigquery-storage; extra == "dev"
Requires-Dist: httpx; extra == "dev"
Requires-Dist: mypy~=1.13.0; extra == "dev"
Requires-Dist: numpy; extra == "dev"
Requires-Dist: pandas-stubs; extra == "dev"
Requires-Dist: pre-commit; extra == "dev"
Requires-Dist: psycopg2-binary; extra == "dev"
Requires-Dist: pydantic; extra == "dev"
Requires-Dist: PyAthena[Pandas]; extra == "dev"
Requires-Dist: PyGithub>=2.6.0; extra == "dev"
Requires-Dist: pyodbc>=5.0.0; extra == "dev"
Requires-Dist: pyperf; extra == "dev"
Requires-Dist: pyspark~=3.5.0; extra == "dev"
Requires-Dist: pytest; extra == "dev"
Requires-Dist: pytest-asyncio; extra == "dev"
Requires-Dist: pytest-mock; extra == "dev"
Requires-Dist: pytest-rerunfailures; extra == "dev"
Requires-Dist: pytest-xdist; extra == "dev"
Requires-Dist: pytz; extra == "dev"
Requires-Dist: redshift_connector; extra == "dev"
Requires-Dist: ruff~=0.11.0; extra == "dev"
Requires-Dist: snowflake-connector-python[pandas,secure-local-storage]>=3.0.2; extra == "dev"
Requires-Dist: sqlalchemy-stubs; extra == "dev"
Requires-Dist: trino; extra == "dev"
Requires-Dist: types-croniter; extra == "dev"
Requires-Dist: types-dateparser; extra == "dev"
Requires-Dist: types-PyMySQL; extra == "dev"
Requires-Dist: types-python-dateutil; extra == "dev"
Requires-Dist: types-pytz; extra == "dev"
Requires-Dist: types-requests==2.28.8; extra == "dev"
Requires-Dist: typing-extensions; extra == "dev"
Provides-Extra: dbt
Requires-Dist: dbt-core<2; extra == "dbt"
Provides-Extra: dlt
Requires-Dist: dlt; extra == "dlt"
Provides-Extra: duckdb
Provides-Extra: fabric
Requires-Dist: pyodbc>=5.0.0; extra == "fabric"
Provides-Extra: gcppostgres
Requires-Dist: cloud-sql-python-connector[pg8000]>=1.8.0; extra == "gcppostgres"
Provides-Extra: github
Requires-Dist: PyGithub>=2.6.0; extra == "github"
Provides-Extra: motherduck
Requires-Dist: duckdb>=1.2.0; extra == "motherduck"
Provides-Extra: mssql
Requires-Dist: pymssql; extra == "mssql"
Provides-Extra: mssql-odbc
Requires-Dist: pyodbc>=5.0.0; extra == "mssql-odbc"
Provides-Extra: mysql
Requires-Dist: pymysql; extra == "mysql"
Provides-Extra: mwaa
Requires-Dist: boto3; extra == "mwaa"
Provides-Extra: postgres
Requires-Dist: psycopg2; extra == "postgres"
Provides-Extra: redshift
Requires-Dist: redshift_connector; extra == "redshift"
Provides-Extra: slack
Requires-Dist: slack_sdk; extra == "slack"
Provides-Extra: snowflake
Requires-Dist: cryptography<46.0.0; extra == "snowflake"
Requires-Dist: snowflake-connector-python[pandas,secure-local-storage]; extra == "snowflake"
Requires-Dist: snowflake-snowpark-python; extra == "snowflake"
Provides-Extra: trino
Requires-Dist: trino; extra == "trino"
Provides-Extra: web
Requires-Dist: fastapi==0.115.5; extra == "web"
Requires-Dist: watchfiles>=0.19.0; extra == "web"
Requires-Dist: uvicorn[standard]==0.22.0; extra == "web"
Requires-Dist: sse-starlette>=0.2.2; extra == "web"
Requires-Dist: pyarrow; extra == "web"
Provides-Extra: lsp
Requires-Dist: fastapi==0.115.5; extra == "lsp"
Requires-Dist: watchfiles>=0.19.0; extra == "lsp"
Requires-Dist: sse-starlette>=0.2.2; extra == "lsp"
Requires-Dist: pyarrow; extra == "lsp"
Requires-Dist: pygls<2.0.0,>=1.2.0; extra == "lsp"
Requires-Dist: lsprotocol; extra == "lsp"
Provides-Extra: risingwave
Requires-Dist: psycopg2; extra == "risingwave"
Dynamic: license-file
